recsys_bpr/__init__.py
recsys_bpr/bpr.py
recsys_bpr/utils.py
recsys_bpr-0.1.1.dist-info/DESCRIPTION.rst
recsys_bpr-0.1.1.dist-info/METADATA
recsys_bpr-0.1.1.dist-info/RECORD
recsys_bpr-0.1.1.dist-info/WHEEL
recsys_bpr-0.1.1.dist-info/metadata.json
recsys_bpr-0.1.1.dist-info/top_level.txt
