Metadata-Version: 2.0
Name: recsys-bpr
Version: 0.1.1
Summary: Bayesian Personalised Ranking implemented in Theano
Home-page: UNKNOWN
Author: Harsh Gupta
Author-email: harshgupta.bbps@gmail.com
License: Apache License 2.0
Platform: UNKNOWN
Requires-Dist: numpy
Requires-Dist: theano
